aptdetector
