Metadata-Version: 1.1
Name: aptdetector
Version: 0.1.4
Summary: Advanced Persistent Threat Detection by Using Network Analysis.
Home-page: https://github.com/abzcoding/aptdetector
Author: Abouzar Parvan
Author-email: abzcoding@gmail.com
License: BSD
Platform: linux_x86_64
Classifier: Topic :: Security
Classifier: Intended Audience :: Education
Classifier: Topic :: System :: Networking
Classifier: Development Status :: 2 - Pre-Alpha
Classifier: Programming Language :: Python :: 3.4
Classifier: Programming Language :: Python :: 3.5
